{
  "hiragana": {
    "あ": "a",
    "い": "i",
    "う": "u",
    "え": "e",
    "お": "o",
    "か": "ka",
    "き": "ki",
    "く": "ku",
    "け": "ke",
    "こ": "ko",
    "が": "ga",
    "ぎ": "gi",
    "ぐ": "gu",
    "げ": "ge",
    "ご": "go",
    "さ": "sa",
    "し": "shi",
    "す": "su",
    "せ": "se",
    "そ": "so",
    "ざ": "za",
    "じ": "ji",
    "ず": "zu",
    "ぜ": "ze",
    "ぞ": "zo",
    "た": "ta",
    "ち": "chi",
    "つ": "tsu",
    "て": "te",
    "と": "to",
    "だ": "da",
    "ぢ": "ji",
    "づ": "zu",
    "で": "de",
    "ど": "do",
    "な": "na",
    "に": "ni",
    "ぬ": "nu",
    "ね": "ne",
    "の": "no",
    "は": "ha",
    "ひ": "hi",
    "ふ": "fu",
    "へ": "he",
    "ほ": "ho",
    "ば": "ba",
    "び": "bi",
    "ぶ": "bu",
    "べ": "be",
    "ぼ": "bo",
    "ぱ": "pa",
    "ぴ": "pi",
    "ぷ": "pu",
    "ぺ": "pe",
    "ぽ": "po",
    "ま": "ma",
    "み": "mi",
    "む": "mu",
    "め": "me",
    "も": "mo",
    "や": "ya",
    "ゆ": "yu",
    "よ": "yo",
    "ら": "ra",
    "り": "ri",
    "る": "ru",
    "れ": "re",
    "ろ": "ro",
    "わ": "wa",
    "を": "wo",
    "ん": "n",
    "きゃ": "kya",
    "きゅ": "kyu",
    "きょ": "kyo",
    "しゃ": "sha",
    "しゅ": "shu",
    "しょ": "sho",
    "ちゃ": "cha",
    "ちゅ": "chu",
    "ちょ": "cho",
    "にゃ": "nya",
    "にゅ": "nyu",
    "にょ": "nyo",
    "ひゃ": "hya",
    "ひゅ": "hyu",
    "ひょ": "hyo",
    "みゃ": "mya",
    "みゅ": "myu",
    "みょ": "myo",
    "りゃ": "rya",
    "りゅ": "ryu",
    "りょ": "ryo",
    "ぎゃ": "gya",
    "ぎゅ": "gyu",
    "ぎょ": "gyo",
    "じゃ": "ja",
    "じゅ": "ju",
    "じょ": "jo",
    "びゃ": "bya",
    "びゅ": "byu",
    "びょ": "byo",
    "ぴゃ": "pya",
    "ぴゅ": "pyu",
    "ぴょ": "pyo"
  },
  "katakana": {
    "ア": "a",
    "イ": "i",
    "ウ": "u",
    "エ": "e",
    "オ": "o",
    "カ": "ka",
    "キ": "ki",
    "ク": "ku",
    "ケ": "ke",
    "コ": "ko",
    "ガ": "ga",
    "ギ": "gi",
    "グ": "gu",
    "ゲ": "ge",
    "ゴ": "go",
    "サ": "sa",
    "シ": "shi",
    "ス": "su",
    "セ": "se",
    "ソ": "so",
    "ザ": "za",
    "ジ": "ji",
    "ズ": "zu",
    "ゼ": "ze",
    "ゾ": "zo",
    "タ": "ta",
    "チ": "chi",
    "ツ": "tsu",
    "テ": "te",
    "ト": "to",
    "ダ": "da",
    "ヂ": "ji",
    "ヅ": "zu",
    "デ": "de",
    "ド": "do",
    "ナ": "na",
    "ニ": "ni",
    "ヌ": "nu",
    "ネ": "ne",
    "ノ": "no",
    "ハ": "ha",
    "ヒ": "hi",
    "フ": "fu",
    "ヘ": "he",
    "ホ": "ho",
    "バ": "ba",
    "ビ": "bi",
    "ブ": "bu",
    "ベ": "be",
    "ボ": "bo",
    "パ": "pa",
    "ピ": "pi",
    "プ": "pu",
    "ペ": "pe",
    "ポ": "po",
    "マ": "ma",
    "ミ": "mi",
    "ム": "mu",
    "メ": "me",
    "モ": "mo",
    "ヤ": "ya",
    "ユ": "yu",
    "ヨ": "yo",
    "ラ": "ra",
    "リ": "ri",
    "ル": "ru",
    "レ": "re",
    "ロ": "ro",
    "ワ": "wa",
    "ヲ": "wo",
    "ン": "n",
    "キャ": "kya",
    "キュ": "kyu",
    "キョ": "kyo",
    "シャ": "sha",
    "シュ": "shu",
    "ショ": "sho",
    "チャ": "cha",
    "チュ": "chu",
    "チョ": "cho",
    "ニャ": "nya",
    "ニュ": "nyu",
    "ニョ": "nyo",
    "ヒャ": "hya",
    "ヒュ": "hyu",
    "ヒョ": "hyo",
    "ミャ": "mya",
    "ミュ": "myu",
    "ミョ": "myo",
    "リャ": "rya",
    "リュ": "ryu",
    "リョ": "ryo",
    "ギャ": "gya",
    "ギュ": "gyu",
    "ギョ": "gyo",
    "ジャ": "ja",
    "ジュ": "ju",
    "ジョ": "jo",
    "ビャ": "bya",
    "ビュ": "byu",
    "ビョ": "byo",
    "ピャ": "pya",
    "ピュ": "pyu",
    "ピョ": "pyo"
  },
  "palabras": {
    "Empresa": "かいしゃ",
    "Banco": "ぎんこう",
    "empleado de empresa": "かいしゃいん",
    "empleado": "しゃいん",
    "Empleado de banco": "ぎんこういん",
    "Investigador": "けんきゅうしゃ",
    "médico": "いしゃ",
    "profesor": "きょうし・せんせい",
    "yo": "わたし",
    "tu": "あなた",
    "nosotros": "わたしたち",
    "estudiante": "がくせい",
    "japones": "にほんご",
    "china": "ちゅうごく",
    "corea": "かんこく",
    "pais": "くに",
    "trabajo": "しごと",
    "hospital": "びょういん",
    "universidad": "だいがく",
    "persona": "ひと",
    "nombre": "なまえ"
  },
  "palabras_J_E": {
    "あい": "AMOR",
    "あう": "REUNIRSE",
    "うえ": "ARRIBA",
    "いえ": "CASA",
    "あお": "AZUL",
    "あか": "ROJO",
    "かお": "CARA",
    "かく": "ESCRIBIR",
    "こい": "VEN",
    "いす": "SILLA",
    "あさ": "LA MAÑANA",
    "しお": "SAL",
    "かさ": "PARAGUAS",
    "おはよう(ございます)": "BUENOS DÍAS",
    "こんにちは": "HOLA (DE DÍA)",
    "こんばんは": "HOLA (DE NOCHE)",
    "おやすみ(なさい)": "BUENAS NOCHES",
    "さようなら": "ADIÓS FORMAL",
    "いってきます": "EXPRESIÓN AL IRSE",
    "いってらっしゃい": "EXPRESIÓN DE DESPEDIDA",
    "ただいま": "EXPRESIÓN DE REGRESO",
    "おかえり(なさい)": "BIENVENIDO DE VUELTA",
    "おねがいします": "POR FAVOR",
    "すみません": "DISCULPE",
    "ごめん(なさい)": "PERDÓN",
    "(どうも)ありがとう(ございます)": "(MUCHAS) GRACIAS",
    "いただきます": "ANTES → GRACIAS POR LA COMIDA",
    "ごちそうさま(でした)": "DESPUÉS → GRACIAS POR LA COMIDA",
    "かんぱい": "SALUD",
    "ほん": "LIBRO",
    "じしょ": "DICCIONARIO",
    "ざっし": "REVISTA",
    "ノート": "CUADERNO",
    "しんぶん": "PERIÓDICO",
    "てちょう": "AGENDA",
    "めいし": "TARJETA DE PRESENTACIÓN",
    "カード": "TARJETA",
    "えんぴつ": "LÁPIZ",
    "ボールペン": "BOLÍGRAFO",
    "シャープペンシル": "PORTAMINAS",
    "かぎ": "LLAVES",
    "とけい": "RELOJ",
    "かばん": "MOCHILA",
    "テレビ": "TELEVISOR",
    "ラジオ": "RADIO",
    "カメラ": "CÁMARA",
    "コンピューター": "COMPUTADORA",
    "じどうしゃ": "AUTOMÓVIL",
    "つくえ": "ESCRITORIO",
    "チョコレート": "CHOCOLATE",
    "しか": "CIERVO",
    "かず": "CANTIDAD",
    "さす": "SEÑALAR",
    "けす": "BORRAR",
    "かげ": "SOMBRA",
    "かぜ": "VIENTO",
    "あじ": "SABOR",
    "さき": "ANTES",
    "たつ": "PONERSE DE PIE",
    "ちず": "MAPA",
    "えだ": "RAMA",
    "とし": "AÑO",
    "くち": "BOCA",
    "つづく": "CONTINUAR",
    "たてがき": "ESCRITURA VERTICAL",
    "ちか": "SUBSUELO",
    "かつ": "GANAR, VENCER",
    "そと": "AFUERA",
    "なに": "¿QUÉ?",
    "ぬの": "TELA",
    "あに": "HERMANO MAYOR",
    "ねこ": "GATO",
    "おかね": "DINERO",
    "なか": "ADENTRO",
    "におい": "OLOR",
    "いぬ": "PERRO",
    "おに": "DEMONIO",
    "へび": "SERPIENTE",
    "かべ": "PARED",
    "はは": "(MI) MADRE",
    "たいふう": "TIFÓN",
    "ほし": "ESTRELLA",
    "ほね": "HUESO",
    "はなび": "FUEGOS ARTIFICIALES",
    "ふね": "BARCO",
    "おげんきですか。": "¿CÓMO ESTÁS?",
    "ひさしぶりです!": "¡TANTO TIEMPO!",
    "どうしましたか。": "¿QUÉ TE SUCEDE?",
    "おだいじに": "QUE TE MEJORES",
    "おつかれ(さまです)": "GRACIAS POR TU TRABAJO",
    "ごくろうさまです": "BUEN TRABAJO (JEFE)",
    "きをつけて(ください)": "CUÍDATE",
    "いいたびを!": "¡BUEN VIAJE!",
    "はな": "FLOR",
    "たばこ": "TABACO",
    "ぶた": "CERDO",
    "たこ": "PULPO",
    "ひつじ": "OVEJA",
    "うけつけ": "RECEPCIÓN",
    "うし": "VACA",
    "した": "ABAJO",
    "あいだ": "ENTRE",
    "はちこ": "HACHIKO",
    "ちち": "(MI) PADRE",
    "おじ": "(MI) TÍO",
    "おば": "(MI) TÍA",
    "あつい": "CALIENTE",
    "くつ": "ZAPATOS",
    "くつした": "CALCETINES",
    "あそこ": "ALLÍ",
    "もも": "DURAZNO",
    "みみ": "OREJA",
    "ひみつ": "SECRETO",
    "まち": "CIUDAD",
    "むだ": "DESPERDICIO",
    "みなと": "PUERTO",
    "もの": "COSA",
    "かいもの": "COMPRAS",
    "たべもの": "ALIMENTOS",
    "め": "OJO",
    "ふゆ": "INVIERNO",
    "ゆき": "NIEVE",
    "よい": "BUENO",
    "やきにく": "CARNE ASADA",
    "よみもの": "COSAS PARA LEER",
    "いや": "INDESEABLE",
    "よこ": "LADO",
    "まる": "CÍRCULO",
    "らく": "FÁCIL",
    "れい": "EJEMPLO",
    "しろ": "BLANCO",
    "はり": "AGUJA",
    "やきとり": "POLLO ASADO",
    "よろこぶ": "ALEGRARSE",
    "いろいろ": "VARIOS",
    "わるい": "MALO",
    "へいわ": "PAZ",
    "かん": "LATA",
    "びん": "BOTELLA",
    "としをとる": "ENVEJECER",
    "かいしゃ": "EMPRESA",
    "ぎんこう": "BANCO",
    "かいしゃいん": "EMPLEADO DE EMPRESA",
    "しゃいん": "EMPLEADO",
    "ぎんこういん": "EMPLEADO DE BANCO",
    "けんきゅうしゃ": "INVESTIGADOR",
    "きょうし": "PROFESOR",
    "せんせい": "PROFESOR",
    "わたし": "YO",
    "あなた": "TÚ",
    "わたしたち": "NOSOTROS",
    "がくせい": "ESTUDIANTE",
    "アルゼンチン": "ARGENTINA",
    "スペイン": "ESPAÑA",
    "メキシコ": "MÉXICO",
    "ドイツ": "ALEMANIA",
    "コロンビア": "COLOMBIA",
    "ペルー": "PERÚ",
    "イギリス": "INGLATERRA",
    "チリ": "CHILE",
    "コスタリカ": "COSTA RICA",
    "エクアドル": "ECUADOR",
    "ウルグアイ": "URUGUAY",
    "イタリア": "ITALIA"
  },
  "palabras_E_J":{
    "AMOR": "あい",
    "REUNIRSE": "あう",
    "ARRIBA": "うえ",
    "CASA": "いえ",
    "AZUL": "あお",
    "ROJO": "あか",
    "CARA": "かお",
    "ESCRIBIR": "かく",
    "VEN": "こい",
    "SILLA": "いす",
    "LA MAÑANA": "あさ",
    "SAL": "しお",
    "PARAGUAS": "かさ",
    "BUENOS DÍAS": "おはよう(ございます)",
    "HOLA (DE DÍA)": "こんにちは",
    "HOLA (DE NOCHE)": "こんばんは",
    "BUENAS NOCHES": "おやすみ(なさい)",
    "ADIÓS FORMAL": "さようなら",
    "EXPRESIÓN AL IRSE": "いってきます",
    "EXPRESIÓN DE DESPEDIDA": "いってらっしゃい",
    "EXPRESIÓN DE REGRESO": "ただいま",
    "BIENVENIDO DE VUELTA": "おかえり(なさい)",
    "POR FAVOR": "おねがいします",
    "DISCULPE": "すみません",
    "PERDÓN": "ごめん(なさい)",
    "(MUCHAS) GRACIAS": "(どうも)ありがとう(ございます)",
    "ANTES → GRACIAS POR LA COMIDA": "いただきます",
    "DESPUÉS → GRACIAS POR LA COMIDA": "ごちそうさま(でした)",
    "SALUD": "かんぱい",
    "LIBRO": "ほん",
    "DICCIONARIO": "じしょ",
    "REVISTA": "ざっし",
    "CUADERNO": "ノート",
    "PERIÓDICO": "しんぶん",
    "AGENDA": "てちょう",
    "TARJETA DE PRESENTACIÓN": "めいし",
    "TARJETA": "カード",
    "LÁPIZ": "えんぴつ",
    "BOLÍGRAFO": "ボールペン",
    "PORTAMINAS": "シャープペンシル",
    "LLAVES": "かぎ",
    "RELOJ": "とけい",
    "MOCHILA": "かばん",
    "TELEVISOR": "テレビ",
    "RADIO": "ラジオ",
    "CÁMARA": "カメラ",
    "COMPUTADORA": "コンピューター",
    "AUTOMÓVIL": "じどうしゃ",
    "ESCRITORIO": "つくえ",
    "CHOCOLATE": "チョコレート",
    "CIERVO": "しか",
    "CANTIDAD": "かず",
    "SEÑALAR": "さす",
    "BORRAR": "けす",
    "SOMBRA": "かげ",
    "VIENTO": "かぜ",
    "SABOR": "あじ",
    "ANTES": "さき",
    "PONERSE DE PIE": "たつ",
    "MAPA": "ちず",
    "RAMA": "えだ",
    "AÑO": "とし",
    "BOCA": "くち",
    "CONTINUAR": "つづく",
    "ESCRITURA VERTICAL": "たてがき",
    "SUBSUELO": "ちか",
    "GANAR, VENCER": "かつ",
    "AFUERA": "そと",
    "¿QUÉ?": "なに",
    "TELA": "ぬの",
    "HERMANO MAYOR": "あに",
    "GATO": "ねこ",
    "DINERO": "おかね",
    "ADENTRO": "なか",
    "OLOR": "におい",
    "PERRO": "いぬ",
    "DEMONIO": "おに",
    "SERPIENTE": "へび",
    "PARED": "かべ",
    "(MI) MADRE": "はは",
    "TIFÓN": "たいふう",
    "ESTRELLA": "ほし",
    "HUESO": "ほね",
    "FUEGOS ARTIFICIALES": "はなび",
    "BARCO": "ふね",
    "¿CÓMO ESTÁS?": "おげんきですか。",
    "¡TANTO TIEMPO!": "ひさしぶりです!",
    "¿QUÉ TE SUCEDE?": "どうしましたか。",
    "QUE TE MEJORES": "おだいじに",
    "GRACIAS POR TU TRABAJO": "おつかれ(さまです)",
    "BUEN TRABAJO (JEFE)": "ごくろうさまです",
    "CUÍDATE": "きをつけて(ください)",
    "¡BUEN VIAJE!": "いいたびを!",
    "FLOR": "はな",
    "TABACO": "たばこ",
    "CERDO": "ぶた",
    "PULPO": "たこ",
    "OVEJA": "ひつじ",
    "RECEPCIÓN": "うけつけ",
    "VACA": "うし",
    "ABAJO": "した",
    "ENTRE": "あいだ",
    "HACHIKO": "はちこ",
    "(MI) PADRE": "ちち",
    "(MI) TÍO": "おじ",
    "(MI) TÍA": "おば",
    "CALIENTE": "あつい",
    "ZAPATOS": "くつ",
    "CALCETINES": "くつした",
    "ALLÍ": "あそこ",
    "DURAZNO": "もも",
    "OREJA": "みみ",
    "SECRETO": "ひみつ",
    "CIUDAD": "まち",
    "DESPERDICIO": "むだ",
    "PUERTO": "みなと",
    "COSA": "もの",
    "COMPRAS": "かいもの",
    "ALIMENTOS": "たべもの",
    "OJO": "め",
    "INVIERNO": "ふゆ",
    "NIEVE": "ゆき",
    "BUENO": "よい",
    "CARNE ASADA": "やきにく",
    "COSAS PARA LEER": "よみもの",
    "INDESEABLE": "いや",
    "LADO": "よこ",
    "CÍRCULO": "まる",
    "FÁCIL": "らく",
    "EJEMPLO": "れい",
    "BLANCO": "しろ",
    "AGUJA": "はり",
    "POLLO ASADO": "やきとり",
    "ALEGRARSE": "よろこぶ",
    "VARIOS": "いろいろ",
    "MALO": "わるい",
    "PAZ": "へいわ",
    "LATA": "かん",
    "BOTELLA": "びん",
    "ENVEJECER": "としをとる",
    "EMPRESA": "かいしゃ",
    "BANCO": "ぎんこう",
    "EMPLEADO DE EMPRESA": "かいしゃいん",
    "EMPLEADO": "しゃいん",
    "EMPLEADO DE BANCO": "ぎんこういん",
    "INVESTIGADOR": "けんきゅうしゃ",
    "PROFESOR": "きょうし",
    "YO": "わたし",
    "TÚ": "あなた",
    "NOSOTROS": "わたしたち",
    "ESTUDIANTE": "がくせい",
    "ARGENTINA": "アルゼンチン",
    "ESPAÑA": "スペイン",
    "MÉXICO": "メキシコ",
    "ALEMANIA": "ドイツ",
    "COLOMBIA": "コロンビア",
    "PERÚ": "ペルー",
    "INGLATERRA": "イギリス",
    "CHILE": "チリ",
    "COSTA RICA": "コスタリカ",
    "ECUADOR": "エクアドル",
    "URUGUAY": "ウルグアイ",
    "ITALIA": "イタリア"
  },
  "vocabulario_R": {
    "LIBRO": "ほん",
    "DICCIONARIO": "じしょ",
    "REVISTA": "ざっし",
    "CUADERNO": "ノート",
    "PERIÓDICO": "しんぶん",
    "AGENDA": "てちょう",
    "TARJETA DE PRESENTACIÓN": "めいし",
    "TARJETA": "カード",
    "LÁPIZ": "えんぴつ",
    "BOLÍGRAFO": "ボールペン",
    "PORTAMINAS": "シャープペンシル",
    "LLAVES": "かぎ",
    "RELOJ": "とけい",
    "MOCHILA": "かばん",
    "TELEVISOR": "テレビ",
    "RADIO": "ラジオ",
    "CÁMARA": "カメラ",
    "COMPUTADORA": "コンピューター",
    "AUTOMÓVIL": "じどうしゃ",
    "ESCRITORIO": "つくえ",
    "CHOCOLATE": "チョコレート"
  }


}
